[
    {
        "toyName":"fantastk world cup",
        "img":"https://img.freepik.com/free-photo/close-up-athlete-playing-soccer_23-2150845600.jpg?t=st=1696847618~exp=1696851218~hmac=81c03bf4ecdf1470da3b682a4a66897fe3f83bfdc35b73f692883c2c8714fd65&w=1060",
        "id":1,       
         "email":"arifhasan1402@gmail.com",
        "sellerName":"Md Arif Hasan",
        "retting":"4.3",
        "quantity":"15",
        "price":"500",
        "category":"football",
        "description":"Reducing body fat. Building strength, stamina and speed. Training your brain, improving concentration and coordination. Promoting teamwork, being social and boosting your confidence."   
   },
    {
        "toyName":"fantastk world cup",
        "img":"https://img.freepik.com/free-photo/close-up-athlete-playing-soccer_23-2150845600.jpg?t=st=1696847618~exp=1696851218~hmac=81c03bf4ecdf1470da3b682a4a66897fe3f83bfdc35b73f692883c2c8714fd65&w=1060",
        "id":2,       
         "email":"sagur@gmail.com",
        "sellerName":"Sagour",
        "retting":"3.3",
        "quantity":"15",
        "price":"500",
        "category":"cricket",
        "description":"Reducing body fat. Building strength, stamina and speed. Training your brain, improving concentration and coordination. Promoting teamwork, being social and boosting your confidence."   
   },
    {
        "toyName":"fantastk world cup",
        "img":"https://img.freepik.com/free-photo/close-up-athlete-playing-soccer_23-2150845600.jpg?t=st=1696847618~exp=1696851218~hmac=81c03bf4ecdf1470da3b682a4a66897fe3f83bfdc35b73f692883c2c8714fd65&w=1060",
        "id":3,       
         "email":"sagur@gmail.com",
        "sellerName":"Md Arif Hasan",
        "retting":"4.3",
        "quantity":"15",
        "price":"500",
        "category":"cricket",
        "description":"Reducing body fat. Building strength, stamina and speed. Training your brain, improving concentration and coordination. Promoting teamwork, being social and boosting your confidence."   
   },
    {
        "toyName":"fantastk world cup",
        "img":"https://img.freepik.com/free-photo/close-up-athlete-playing-soccer_23-2150845600.jpg?t=st=1696847618~exp=1696851218~hmac=81c03bf4ecdf1470da3b682a4a66897fe3f83bfdc35b73f692883c2c8714fd65&w=1060",
        "id":4,       
         "email":"sagur@gmail.com",
        "sellerName":"Md Arif Hasan",
        "retting":"4.3",
        "quantity":"15",
        "price":"500",
        "category":"cricket",
        "description":"Reducing body fat. Building strength, stamina and speed. Training your brain, improving concentration and coordination. Promoting teamwork, being social and boosting your confidence."   
   },
    {
        "toyName":"fantastk world cup",
        "img":"https://img.freepik.com/free-photo/close-up-athlete-playing-soccer_23-2150845600.jpg?t=st=1696847618~exp=1696851218~hmac=81c03bf4ecdf1470da3b682a4a66897fe3f83bfdc35b73f692883c2c8714fd65&w=1060",
        "id":5,       
         "email":"sagur@gmail.com",
        "sellerName":"Md Arif Hasan",
        "retting":"4.3",
        "quantity":"15",
        "price":"500",
        "category":"football",
        "description":"Reducing body fat. Building strength, stamina and speed. Training your brain, improving concentration and coordination. Promoting teamwork, being social and boosting your confidence."   
   },
    {
        "toyName":"fantastk world cup",
        "img":"https://img.freepik.com/free-photo/close-up-athlete-playing-soccer_23-2150845600.jpg?t=st=1696847618~exp=1696851218~hmac=81c03bf4ecdf1470da3b682a4a66897fe3f83bfdc35b73f692883c2c8714fd65&w=1060",
        "id":6,       
         "email":"arifhasan1402@gmail.com",
        "sellerName":"Md Arif Hasan",
        "retting":"4.3",
        "quantity":"15",
        "price":"500",
        "category":"voliball",
        "description":"Reducing body fat. Building strength, stamina and speed. Training your brain, improving concentration and coordination. Promoting teamwork, being social and boosting your confidence."   
   },
    {
        "toyName":"fantastk world cup",
        "img":"https://img.freepik.com/free-photo/close-up-athlete-playing-soccer_23-2150845600.jpg?t=st=1696847618~exp=1696851218~hmac=81c03bf4ecdf1470da3b682a4a66897fe3f83bfdc35b73f692883c2c8714fd65&w=1060",
        "id":7,       
         "email":"arifhasan1402@gmail.com",
        "sellerName":"Md Arif Hasan",
        "retting":"4.3",
        "quantity":"15",
        "price":"500",
        "category":"voliball",
        "description":"Reducing body fat. Building strength, stamina and speed. Training your brain, improving concentration and coordination. Promoting teamwork, being social and boosting your confidence."   
   },
    {
        "toyName":"fantastk world cup",
        "img":"https://img.freepik.com/free-photo/close-up-athlete-playing-soccer_23-2150845600.jpg?t=st=1696847618~exp=1696851218~hmac=81c03bf4ecdf1470da3b682a4a66897fe3f83bfdc35b73f692883c2c8714fd65&w=1060",
        "id":8,       
         "email":"app@gmail.com",
        "sellerName":"Md Arif Hasan",
        "retting":"4.3",
        "quantity":"15",
        "price":"500",
        "category":"voliball",
        "description":"Reducing body fat. Building strength, stamina and speed. Training your brain, improving concentration and coordination. Promoting teamwork, being social and boosting your confidence."   
   },
    {
        "toyName":"fantastk world cup",
        "img":"https://img.freepik.com/free-photo/close-up-athlete-playing-soccer_23-2150845600.jpg?t=st=1696847618~exp=1696851218~hmac=81c03bf4ecdf1470da3b682a4a66897fe3f83bfdc35b73f692883c2c8714fd65&w=1060",
        "id":9,       
         "email":"arifhasan1402@gmail.com",
        "sellerName":"Md Arif Hasan",
        "retting":"4.3",
        "quantity":"15",
        "price":"500",
        "category":"football",
        "description":"Reducing body fat. Building strength, stamina and speed. Training your brain, improving concentration and coordination. Promoting teamwork, being social and boosting your confidence."   
   }
]
